pycounts_am/__init__.py
pycounts_am/plotting.py
pycounts_am/pycounts_am.py
pycounts_am-0.1.0.dist-info/LICENSE
pycounts_am-0.1.0.dist-info/WHEEL
pycounts_am-0.1.0.dist-info/METADATA
pycounts_am-0.1.0.dist-info/RECORD
