Metadata-Version: 2.1
Name: pycounts-am
Version: 0.1.0
Summary: Counting words in a text file.
License: MIT
Author: adammorphy
Requires-Python: >=3.9,<4.0
Classifier: License :: OSI Approved :: MIT License
Classifier: Programming Language :: Python :: 3
Classifier: Programming Language :: Python :: 3.9
Requires-Dist: matplotlib (>=3.5.1,<4.0.0)
